TP1/contador.vhdl
library IEEE;
use ieee.std_logic_1164.all;
use ieee.numeric_std.all;

entity contador is
    generic (
        N3 : natural := 28;
        N30 : natural := 4
    );
    port(
        rst : in std_logic;
        clk : in std_logic;
        tres_segundos  : out std_logic;
        treinta_segundos : out std_logic
    );
end contador;

architecture contador_arq of contador is
    signal aux_cuenta_3  : unsigned(N3-1 downto 0);
    signal aux_cuenta_30 : unsigned(N30-1 downto 0);
    signal aux_tres_segundos:  std_logic := '0';
    signal aux_treinta_segundos:  std_logic := '0';
begin
    process(clk, rst) is
        begin
            if rst = '1' then
                aux_cuenta_3 <= (others => '0');
            elsif clk = '1' and clk'event then
                if aux_tres_segundos = '1' then
                    aux_tres_segundos <= '0';
                end if;
                if aux_cuenta_3 = 20 then
                    aux_cuenta_3 <= (others => '0');
                    aux_tres_segundos <= '1';
                else
                    aux_cuenta_3 <= aux_cuenta_3 + 1;
                end if;
            end if;
        end process;

        process(clk, rst) is
            begin
                if rst = '1' then
                    aux_cuenta_30 <= (others => '0');
                elsif clk = '1' and clk'event then
                    if aux_treinta_segundos = '1' then
                        aux_treinta_segundos <= '0';
                    end if;
                    if aux_tres_segundos = '1' then
                        if aux_cuenta_30 = 9 then
                            aux_cuenta_30 <= (others => '0');
                            aux_treinta_segundos <= '1';
                        else
                            aux_cuenta_30 <= aux_cuenta_30 + 1;
                        end if;
                    end if;
                end if;
            end process;

        tres_segundos    <= aux_tres_segundos;
        treinta_segundos <= aux_treinta_segundos;

end contador_arq;

TP1/tb_contador.vhdl
library ieee;
use ieee.std_logic_1164.all;

entity tb_contador is
end tb_contador;

architecture tb_contador_arq of tb_contador is
    
    component contador is
		port (
			rst : in std_logic;
            clk : in std_logic;
            tres_segundos  : out std_logic;
            treinta_segundos : out std_logic
		);
	end component;
    
    signal tb_clk               : std_logic := '0';
    signal tb_rst               : std_logic;
    signal tb_tres_segundos     : std_logic := '0';    
    signal tb_treinta_segundos  : std_logic := '0';
  
    begin
        tb_rst <= '1', '0' after 1 ns;
        tb_clk <= not tb_clk after 0.10 ns;

    DUT: contador
        port map(
            rst                 => tb_rst,
            clk                 => tb_clk,
            tres_segundos       => tb_tres_segundos,
            treinta_segundos    => tb_treinta_segundos 
    );

    
end tb_contador_arq;

TP1/tb_contador.vcd
$date
  Thu Oct  6 16:16:37 2022
$end
$version
  GHDL v0
$end
$timescale
  1 fs
$end
$scope module standard $end
$upscope $end
$scope module std_logic_1164 $end
$upscope $end
$scope module numeric_std $end
$upscope $end
$scope module tb_contador $end
$var reg 1 ! tb_clk $end
$var reg 1 " tb_rst $end
$var reg 1 # tb_tres_segundos $end
$var reg 1 $ tb_treinta_segundos $end
$scope module dut $end
$var reg 1 % rst $end
$var reg 1 & clk $end
$var reg 1 ' tres_segundos $end
$var reg 1 ( treinta_segundos $end
$var reg 28 ) aux_cuenta_3[27:0] $end
$var reg 4 * aux_cuenta_30[3:0] $end
$var reg 1 + aux_tres_segundos $end
$var reg 1 , aux_treinta_segundos $end
$upscope $end
$upscope $end
$enddefinitions $end
#0
0!
1"
0#
0$
1%
0&
0'
0(
b0000000000000000000000000000 )
b0000 *
0+
0,
#100000
1!
1&
#200000
0!
0&
#300000
1!
1&
#400000
0!
0&
#500000
1!
1&
#600000
0!
0&
#700000
1!
1&
#800000
0!
0&
#900000
1!
1&
#1000000
0!
0"
0%
0&
#1100000
1!
1&
b0000000000000000000000000001 )
#1200000
0!
0&
#1300000
1!
1&
b0000000000000000000000000010 )
#1400000
0!
0&
#1500000
1!
1&
b0000000000000000000000000011 )
#1600000
0!
0&
#1700000
1!
1&
b0000000000000000000000000100 )
#1800000
0!
0&
#1900000
1!
1&
b0000000000000000000000000101 )
#2000000
0!
0&
#2100000
1!
1&
b0000000000000000000000000110 )
#2200000
0!
0&
#2300000
1!
1&
b0000000000000000000000000111 )
#2400000
0!
0&
#2500000
1!
1&
b0000000000000000000000001000 )
#2600000
0!
0&
#2700000
1!
1&
b0000000000000000000000001001 )
#2800000
0!
0&
#2900000
1!
1&
b0000000000000000000000001010 )
#3000000
0!
0&
#3100000
1!
1&
b0000000000000000000000001011 )
#3200000
0!
0&
#3300000
1!
1&
b0000000000000000000000001100 )
#3400000
0!
0&
#3500000
1!
1&
b0000000000000000000000001101 )
#3600000
0!
0&
#3700000
1!
1&
b0000000000000000000000001110 )
#3800000
0!
0&
#3900000
1!
1&
b0000000000000000000000001111 )
#4000000
0!
0&
#4100000
1!
1&
b0000000000000000000000010000 )
#4200000
0!
0&
#4300000
1!
1&
b0000000000000000000000010001 )
#4400000
0!
0&
#4500000
1!
1&
b0000000000000000000000010010 )
#4600000
0!
0&
#4700000
1!
1&
b0000000000000000000000010011 )
#4800000
0!
0&
#4900000
1!
1&
b0000000000000000000000010100 )
#5000000
0!
0&
#5100000
1!
1#
1&
1'
b0000000000000000000000000000 )
1+
#5200000
0!
0&
#5300000
1!
0#
1&
0'
b0000000000000000000000000001 )
b0001 *
0+
#5400000
0!
0&
#5500000
1!
1&
b0000000000000000000000000010 )
#5600000
0!
0&
#5700000
1!
1&
b0000000000000000000000000011 )
#5800000
0!
0&
#5900000
1!
1&
b0000000000000000000000000100 )
#6000000
0!
0&
#6100000
1!
1&
b0000000000000000000000000101 )
#6200000
0!
0&
#6300000
1!
1&
b0000000000000000000000000110 )
#6400000
0!
0&
#6500000
1!
1&
b0000000000000000000000000111 )
#6600000
0!
0&
#6700000
1!
1&
b0000000000000000000000001000 )
#6800000
0!
0&
#6900000
1!
1&
b0000000000000000000000001001 )
#7000000
0!
0&
#7100000
1!
1&
b0000000000000000000000001010 )
#7200000
0!
0&
#7300000
1!
1&
b0000000000000000000000001011 )
#7400000
0!
0&
#7500000
1!
1&
b0000000000000000000000001100 )
#7600000
0!
0&
#7700000
1!
1&
b0000000000000000000000001101 )
#7800000
0!
0&
#7900000
1!
1&
b0000000000000000000000001110 )
#8000000
0!
0&
#8100000
1!
1&
b0000000000000000000000001111 )
#8200000
0!
0&
#8300000
1!
1&
b0000000000000000000000010000 )
#8400000
0!
0&
#8500000
1!
1&
b0000000000000000000000010001 )
#8600000
0!
0&
#8700000
1!
1&
b0000000000000000000000010010 )
#8800000
0!
0&
#8900000
1!
1&
b0000000000000000000000010011 )
#9000000
0!
0&
#9100000
1!
1&
b0000000000000000000000010100 )
#9200000
0!
0&
#9300000
1!
1#
1&
1'
b0000000000000000000000000000 )
1+
#9400000
0!
0&
#9500000
1!
0#
1&
0'
b0000000000000000000000000001 )
b0010 *
0+
#9600000
0!
0&
#9700000
1!
1&
b0000000000000000000000000010 )
#9800000
0!
0&
#9900000
1!
1&
b0000000000000000000000000011 )
#10000000
0!
0&
#10100000
1!
1&
b0000000000000000000000000100 )
#10200000
0!
0&
#10300000
1!
1&
b0000000000000000000000000101 )
#10400000
0!
0&
#10500000
1!
1&
b0000000000000000000000000110 )
#10600000
0!
0&
#10700000
1!
1&
b0000000000000000000000000111 )
#10800000
0!
0&
#10900000
1!
1&
b0000000000000000000000001000 )
#11000000
0!
0&
#11100000
1!
1&
b0000000000000000000000001001 )
#11200000
0!
0&
#11300000
1!
1&
b0000000000000000000000001010 )
#11400000
0!
0&
#11500000
1!
1&
b0000000000000000000000001011 )
#11600000
0!
0&
#11700000
1!
1&
b0000000000000000000000001100 )
#11800000
0!
0&
#11900000
1!
1&
b0000000000000000000000001101 )
#12000000
0!
0&
#12100000
1!
1&
b0000000000000000000000001110 )
#12200000
0!
0&
#12300000
1!
1&
b0000000000000000000000001111 )
#12400000
0!
0&
#12500000
1!
1&
b0000000000000000000000010000 )
#12600000
0!
0&
#12700000
1!
1&
b0000000000000000000000010001 )
#12800000
0!
0&
#12900000
1!
1&
b0000000000000000000000010010 )
#13000000
0!
0&
#13100000
1!
1&
b0000000000000000000000010011 )
#13200000
0!
0&
#13300000
1!
1&
b0000000000000000000000010100 )
#13400000
0!
0&
#13500000
1!
1#
1&
1'
b0000000000000000000000000000 )
1+
#13600000
0!
0&
#13700000
1!
0#
1&
0'
b0000000000000000000000000001 )
b0011 *
0+
#13800000
0!
0&
#13900000
1!
1&
b0000000000000000000000000010 )
#14000000
0!
0&
#14100000
1!
1&
b0000000000000000000000000011 )
#14200000
0!
0&
#14300000
1!
1&
b0000000000000000000000000100 )
#14400000
0!
0&
#14500000
1!
1&
b0000000000000000000000000101 )
#14600000
0!
0&
#14700000
1!
1&
b0000000000000000000000000110 )
#14800000
0!
0&
#14900000
1!
1&
b0000000000000000000000000111 )
#15000000
0!
0&
#15100000
1!
1&
b0000000000000000000000001000 )
#15200000
0!
0&
#15300000
1!
1&
b0000000000000000000000001001 )
#15400000
0!
0&
#15500000
1!
1&
b0000000000000000000000001010 )
#15600000
0!
0&
#15700000
1!
1&
b0000000000000000000000001011 )
#15800000
0!
0&
#15900000
1!
1&
b0000000000000000000000001100 )
#16000000
0!
0&
#16100000
1!
1&
b0000000000000000000000001101 )
#16200000
0!
0&
#16300000
1!
1&
b0000000000000000000000001110 )
#16400000
0!
0&
#16500000
1!
1&
b0000000000000000000000001111 )
#16600000
0!
0&
#16700000
1!
1&
b0000000000000000000000010000 )
#16800000
0!
0&
#16900000
1!
1&
b0000000000000000000000010001 )
#17000000
0!
0&
#17100000
1!
1&
b0000000000000000000000010010 )
#17200000
0!
0&
#17300000
1!
1&
b0000000000000000000000010011 )
#17400000
0!
0&
#17500000
1!
1&
b0000000000000000000000010100 )
#17600000
0!
0&
#17700000
1!
1#
1&
1'
b0000000000000000000000000000 )
1+
#17800000
0!
0&
#17900000
1!
0#
1&
0'
b0000000000000000000000000001 )
b0100 *
0+
#18000000
0!
0&
#18100000
1!
1&
b0000000000000000000000000010 )
#18200000
0!
0&
#18300000
1!
1&
b0000000000000000000000000011 )
#18400000
0!
0&
#18500000
1!
1&
b0000000000000000000000000100 )
#18600000
0!
0&
#18700000
1!
1&
b0000000000000000000000000101 )
#18800000
0!
0&
#18900000
1!
1&
b0000000000000000000000000110 )
#19000000
0!
0&
#19100000
1!
1&
b0000000000000000000000000111 )
#19200000
0!
0&
#19300000
1!
1&
b0000000000000000000000001000 )
#19400000
0!
0&
#19500000
1!
1&
b0000000000000000000000001001 )
#19600000
0!
0&
#19700000
1!
1&
b0000000000000000000000001010 )
#19800000
0!
0&
#19900000
1!
1&
b0000000000000000000000001011 )
#20000000
0!
0&
#20100000
1!
1&
b0000000000000000000000001100 )
#20200000
0!
0&
#20300000
1!
1&
b0000000000000000000000001101 )
#20400000
0!
0&
#20500000
1!
1&
b0000000000000000000000001110 )
#20600000
0!
0&
#20700000
1!
1&
b0000000000000000000000001111 )
#20800000
0!
0&
#20900000
1!
1&
b0000000000000000000000010000 )
#21000000
0!
0&
#21100000
1!
1&
b0000000000000000000000010001 )
#21200000
0!
0&
#21300000
1!
1&
b0000000000000000000000010010 )
#21400000
0!
0&
#21500000
1!
1&
b0000000000000000000000010011 )
#21600000
0!
0&
#21700000
1!
1&
b0000000000000000000000010100 )
#21800000
0!
0&
#21900000
1!
1#
1&
1'
b0000000000000000000000000000 )
1+
#22000000
0!
0&
#22100000
1!
0#
1&
0'
b0000000000000000000000000001 )
b0101 *
0+
#22200000
0!
0&
#22300000
1!
1&
b0000000000000000000000000010 )
#22400000
0!
0&
#22500000
1!
1&
b0000000000000000000000000011 )
#22600000
0!
0&
#22700000
1!
1&
b0000000000000000000000000100 )
#22800000
0!
0&
#22900000
1!
1&
b0000000000000000000000000101 )
#23000000
0!
0&
#23100000
1!
1&
b0000000000000000000000000110 )
#23200000
0!
0&
#23300000
1!
1&
b0000000000000000000000000111 )
#23400000
0!
0&
#23500000
1!
1&
b0000000000000000000000001000 )
#23600000
0!
0&
#23700000
1!
1&
b0000000000000000000000001001 )
#23800000
0!
0&
#23900000
1!
1&
b0000000000000000000000001010 )
#24000000
0!
0&
#24100000
1!
1&
b0000000000000000000000001011 )
#24200000
0!
0&
#24300000
1!
1&
b0000000000000000000000001100 )
#24400000
0!
0&
#24500000
1!
1&
b0000000000000000000000001101 )
#24600000
0!
0&
#24700000
1!
1&
b0000000000000000000000001110 )
#24800000
0!
0&
#24900000
1!
1&
b0000000000000000000000001111 )
#25000000
0!
0&
#25100000
1!
1&
b0000000000000000000000010000 )
#25200000
0!
0&
#25300000
1!
1&
b0000000000000000000000010001 )
#25400000
0!
0&
#25500000
1!
1&
b0000000000000000000000010010 )
#25600000
0!
0&
#25700000
1!
1&
b0000000000000000000000010011 )
#25800000
0!
0&
#25900000
1!
1&
b0000000000000000000000010100 )
#26000000
0!
0&
#26100000
1!
1#
1&
1'
b0000000000000000000000000000 )
1+
#26200000
0!
0&
#26300000
1!
0#
1&
0'
b0000000000000000000000000001 )
b0110 *
0+
#26400000
0!
0&
#26500000
1!
1&
b0000000000000000000000000010 )
#26600000
0!
0&
#26700000
1!
1&
b0000000000000000000000000011 )
#26800000
0!
0&
#26900000
1!
1&
b0000000000000000000000000100 )
#27000000
0!
0&
#27100000
1!
1&
b0000000000000000000000000101 )
#27200000
0!
0&
#27300000
1!
1&
b0000000000000000000000000110 )
#27400000
0!
0&
#27500000
1!
1&
b0000000000000000000000000111 )
#27600000
0!
0&
#27700000
1!
1&
b0000000000000000000000001000 )
#27800000
0!
0&
#27900000
1!
1&
b0000000000000000000000001001 )
#28000000
0!
0&
#28100000
1!
1&
b0000000000000000000000001010 )
#28200000
0!
0&
#28300000
1!
1&
b0000000000000000000000001011 )
#28400000
0!
0&
#28500000
1!
1&
b0000000000000000000000001100 )
#28600000
0!
0&
#28700000
1!
1&
b0000000000000000000000001101 )
#28800000
0!
0&
#28900000
1!
1&
b0000000000000000000000001110 )
#29000000
0!
0&
#29100000
1!
1&
b0000000000000000000000001111 )
#29200000
0!
0&
#29300000
1!
1&
b0000000000000000000000010000 )
#29400000
0!
0&
#29500000
1!
1&
b0000000000000000000000010001 )
#29600000
0!
0&
#29700000
1!
1&
b0000000000000000000000010010 )
#29800000
0!
0&
#29900000
1!
1&
b0000000000000000000000010011 )
#30000000
0!
0&
#30100000
1!
1&
b0000000000000000000000010100 )
#30200000
0!
0&
#30300000
1!
1#
1&
1'
b0000000000000000000000000000 )
1+
#30400000
0!
0&
#30500000
1!
0#
1&
0'
b0000000000000000000000000001 )
b0111 *
0+
#30600000
0!
0&
#30700000
1!
1&
b0000000000000000000000000010 )
#30800000
0!
0&
#30900000
1!
1&
b0000000000000000000000000011 )
#31000000
0!
0&
#31100000
1!
1&
b0000000000000000000000000100 )
#31200000
0!
0&
#31300000
1!
1&
b0000000000000000000000000101 )
#31400000
0!
0&
#31500000
1!
1&
b0000000000000000000000000110 )
#31600000
0!
0&
#31700000
1!
1&
b0000000000000000000000000111 )
#31800000
0!
0&
#31900000
1!
1&
b0000000000000000000000001000 )
#32000000
0!
0&
#32100000
1!
1&
b0000000000000000000000001001 )
#32200000
0!
0&
#32300000
1!
1&
b0000000000000000000000001010 )
#32400000
0!
0&
#32500000
1!
1&
b0000000000000000000000001011 )
#32600000
0!
0&
#32700000
1!
1&
b0000000000000000000000001100 )
#32800000
0!
0&
#32900000
1!
1&
b0000000000000000000000001101 )
#33000000
0!
0&
#33100000
1!
1&
b0000000000000000000000001110 )
#33200000
0!
0&
#33300000
1!
1&
b0000000000000000000000001111 )
#33400000
0!
0&
#33500000
1!
1&
b0000000000000000000000010000 )
#33600000
0!
0&
#33700000
1!
1&
b0000000000000000000000010001 )
#33800000
0!
0&
#33900000
1!
1&
b0000000000000000000000010010 )
#34000000
0!
0&
#34100000
1!
1&
b0000000000000000000000010011 )
#34200000
0!
0&
#34300000
1!
1&
b0000000000000000000000010100 )
#34400000
0!
0&
#34500000
1!
1#
1&
1'
b0000000000000000000000000000 )
1+
#34600000
0!
0&
#34700000
1!
0#
1&
0'
b0000000000000000000000000001 )
b1000 *
0+
#34800000
0!
0&
#34900000
1!
1&
b0000000000000000000000000010 )
#35000000
0!
0&
#35100000
1!
1&
b0000000000000000000000000011 )
#35200000
0!
0&
#35300000
1!
1&
b0000000000000000000000000100 )
#35400000
0!
0&
#35500000
1!
1&
b0000000000000000000000000101 )
#35600000
0!
0&
#35700000
1!
1&
b0000000000000000000000000110 )
#35800000
0!
0&
#35900000
1!
1&
b0000000000000000000000000111 )
#36000000
0!
0&
#36100000
1!
1&
b0000000000000000000000001000 )
#36200000
0!
0&
#36300000
1!
1&
b0000000000000000000000001001 )
#36400000
0!
0&
#36500000
1!
1&
b0000000000000000000000001010 )
#36600000
0!
0&
#36700000
1!
1&
b0000000000000000000000001011 )
#36800000
0!
0&
#36900000
1!
1&
b0000000000000000000000001100 )
#37000000
0!
0&
#37100000
1!
1&
b0000000000000000000000001101 )
#37200000
0!
0&
#37300000
1!
1&
b0000000000000000000000001110 )
#37400000
0!
0&
#37500000
1!
1&
b0000000000000000000000001111 )
#37600000
0!
0&
#37700000
1!
1&
b0000000000000000000000010000 )
#37800000
0!
0&
#37900000
1!
1&
b0000000000000000000000010001 )
#38000000
0!
0&
#38100000
1!
1&
b0000000000000000000000010010 )
#38200000
0!
0&
#38300000
1!
1&
b0000000000000000000000010011 )
#38400000
0!
0&
#38500000
1!
1&
b0000000000000000000000010100 )
#38600000
0!
0&
#38700000
1!
1#
1&
1'
b0000000000000000000000000000 )
1+
#38800000
0!
0&
#38900000
1!
0#
1&
0'
b0000000000000000000000000001 )
b1001 *
0+
#39000000
0!
0&
#39100000
1!
1&
b0000000000000000000000000010 )
#39200000
0!
0&
#39300000
1!
1&
b0000000000000000000000000011 )
#39400000
0!
0&
#39500000
1!
1&
b0000000000000000000000000100 )
#39600000
0!
0&
#39700000
1!
1&
b0000000000000000000000000101 )
#39800000
0!
0&
#39900000
1!
1&
b0000000000000000000000000110 )
#40000000
0!
0&
#40100000
1!
1&
b0000000000000000000000000111 )
#40200000
0!
0&
#40300000
1!
1&
b0000000000000000000000001000 )
#40400000
0!
0&
#40500000
1!
1&
b0000000000000000000000001001 )
#40600000
0!
0&
#40700000
1!
1&
b0000000000000000000000001010 )
#40800000
0!
0&
#40900000
1!
1&
b0000000000000000000000001011 )
#41000000
0!
0&
#41100000
1!
1&
b0000000000000000000000001100 )
#41200000
0!
0&
#41300000
1!
1&
b0000000000000000000000001101 )
#41400000
0!
0&
#41500000
1!
1&
b0000000000000000000000001110 )
#41600000
0!
0&
#41700000
1!
1&
b0000000000000000000000001111 )
#41800000
0!
0&
#41900000
1!
1&
b0000000000000000000000010000 )
#42000000
0!
0&
#42100000
1!
1&
b0000000000000000000000010001 )
#42200000
0!
0&
#42300000
1!
1&
b0000000000000000000000010010 )
#42400000
0!
0&
#42500000
1!
1&
b0000000000000000000000010011 )
#42600000
0!
0&
#42700000
1!
1&
b0000000000000000000000010100 )
#42800000
0!
0&
#42900000
1!
1#
1&
1'
b0000000000000000000000000000 )
1+
#43000000
0!
0&
#43100000
1!
0#
1$
1&
0'
1(
b0000000000000000000000000001 )
b0000 *
0+
1,
#43200000
0!
0&
#43300000
1!
0$
1&
0(
b0000000000000000000000000010 )
0,
#43400000
0!
0&
#43500000
1!
1&
b0000000000000000000000000011 )
#43600000
0!
0&
#43700000
1!
1&
b0000000000000000000000000100 )
#43800000
0!
0&
#43900000
1!
1&
b0000000000000000000000000101 )
#44000000
0!
0&
#44100000
1!
1&
b0000000000000000000000000110 )
#44200000
0!
0&
#44300000
1!
1&
b0000000000000000000000000111 )
#44400000
0!
0&
#44500000
1!
1&
b0000000000000000000000001000 )
#44600000
0!
0&
#44700000
1!
1&
b0000000000000000000000001001 )
#44800000
0!
0&
#44900000
1!
1&
b0000000000000000000000001010 )
#45000000
0!
0&
#45100000
1!
1&
b0000000000000000000000001011 )
#45200000
0!
0&
#45300000
1!
1&
b0000000000000000000000001100 )
#45400000
0!
0&
#45500000
1!
1&
b0000000000000000000000001101 )
#45600000
0!
0&
#45700000
1!
1&
b0000000000000000000000001110 )
#45800000
0!
0&
#45900000
1!
1&
b0000000000000000000000001111 )
#46000000
0!
0&
#46100000
1!
1&
b0000000000000000000000010000 )
#46200000
0!
0&
#46300000
1!
1&
b0000000000000000000000010001 )
#46400000
0!
0&
#46500000
1!
1&
b0000000000000000000000010010 )
#46600000
0!
0&
#46700000
1!
1&
b0000000000000000000000010011 )
#46800000
0!
0&
#46900000
1!
1&
b0000000000000000000000010100 )
#47000000
0!
0&
#47100000
1!
1#
1&
1'
b0000000000000000000000000000 )
1+
#47200000
0!
0&
#47300000
1!
0#
1&
0'
b0000000000000000000000000001 )
b0001 *
0+
#47400000
0!
0&
#47500000
1!
1&
b0000000000000000000000000010 )
#47600000
0!
0&
#47700000
1!
1&
b0000000000000000000000000011 )
#47800000
0!
0&
#47900000
1!
1&
b0000000000000000000000000100 )
#48000000
0!
0&
#48100000
1!
1&
b0000000000000000000000000101 )
#48200000
0!
0&
#48300000
1!
1&
b0000000000000000000000000110 )
#48400000
0!
0&
#48500000
1!
1&
b0000000000000000000000000111 )
#48600000
0!
0&
#48700000
1!
1&
b0000000000000000000000001000 )
#48800000
0!
0&
#48900000
1!
1&
b0000000000000000000000001001 )
#49000000
0!
0&
#49100000
1!
1&
b0000000000000000000000001010 )
#49200000
0!
0&
#49300000
1!
1&
b0000000000000000000000001011 )
#49400000
0!
0&
#49500000
1!
1&
b0000000000000000000000001100 )
#49600000
0!
0&
#49700000
1!
1&
b0000000000000000000000001101 )
#49800000
0!
0&
#49900000
1!
1&
b0000000000000000000000001110 )
#50000000
0!
0&
#50100000
1!
1&
b0000000000000000000000001111 )
#50200000
0!
0&
#50300000
1!
1&
b0000000000000000000000010000 )
#50400000
0!
0&
#50500000
1!
1&
b0000000000000000000000010001 )
#50600000
0!
0&
#50700000
1!
1&
b0000000000000000000000010010 )
#50800000
0!
0&
#50900000
1!
1&
b0000000000000000000000010011 )
#51000000
0!
0&
#51100000
1!
1&
b0000000000000000000000010100 )
#51200000
0!
0&
#51300000
1!
1#
1&
1'
b0000000000000000000000000000 )
1+
#51400000
0!
0&
#51500000
1!
0#
1&
0'
b0000000000000000000000000001 )
b0010 *
0+
#51600000
0!
0&
#51700000
1!
1&
b0000000000000000000000000010 )
#51800000
0!
0&
#51900000
1!
1&
b0000000000000000000000000011 )
#52000000
0!
0&
#52100000
1!
1&
b0000000000000000000000000100 )
#52200000
0!
0&
#52300000
1!
1&
b0000000000000000000000000101 )
#52400000
0!
0&
#52500000
1!
1&
b0000000000000000000000000110 )
#52600000
0!
0&
#52700000
1!
1&
b0000000000000000000000000111 )
#52800000
0!
0&
#52900000
1!
1&
b0000000000000000000000001000 )
#53000000
0!
0&
#53100000
1!
1&
b0000000000000000000000001001 )
#53200000
0!
0&
#53300000
1!
1&
b0000000000000000000000001010 )
#53400000
0!
0&
#53500000
1!
1&
b0000000000000000000000001011 )
#53600000
0!
0&
#53700000
1!
1&
b0000000000000000000000001100 )
#53800000
0!
0&
#53900000
1!
1&
b0000000000000000000000001101 )
#54000000
0!
0&
#54100000
1!
1&
b0000000000000000000000001110 )
#54200000
0!
0&
#54300000
1!
1&
b0000000000000000000000001111 )
#54400000
0!
0&
#54500000
1!
1&
b0000000000000000000000010000 )
#54600000
0!
0&
#54700000
1!
1&
b0000000000000000000000010001 )
#54800000
0!
0&
#54900000
1!
1&
b0000000000000000000000010010 )
#55000000
0!
0&
#55100000
1!
1&
b0000000000000000000000010011 )
#55200000
0!
0&
#55300000
1!
1&
b0000000000000000000000010100 )
#55400000
0!
0&
#55500000
1!
1#
1&
1'
b0000000000000000000000000000 )
1+
#55600000
0!
0&
#55700000
1!
0#
1&
0'
b0000000000000000000000000001 )
b0011 *
0+
#55800000
0!
0&
#55900000
1!
1&
b0000000000000000000000000010 )
#56000000
0!
0&
#56100000
1!
1&
b0000000000000000000000000011 )
#56200000
0!
0&
#56300000
1!
1&
b0000000000000000000000000100 )
#56400000
0!
0&
#56500000
1!
1&
b0000000000000000000000000101 )
#56600000
0!
0&
#56700000
1!
1&
b0000000000000000000000000110 )
#56800000
0!
0&
#56900000
1!
1&
b0000000000000000000000000111 )
#57000000
0!
0&
#57100000
1!
1&
b0000000000000000000000001000 )
#57200000
0!
0&
#57300000
1!
1&
b0000000000000000000000001001 )
#57400000
0!
0&
#57500000
1!
1&
b0000000000000000000000001010 )
#57600000
0!
0&
#57700000
1!
1&
b0000000000000000000000001011 )
#57800000
0!
0&
#57900000
1!
1&
b0000000000000000000000001100 )
#58000000
0!
0&
#58100000
1!
1&
b0000000000000000000000001101 )
#58200000
0!
0&
#58300000
1!
1&
b0000000000000000000000001110 )
#58400000
0!
0&
#58500000
1!
1&
b0000000000000000000000001111 )
#58600000
0!
0&
#58700000
1!
1&
b0000000000000000000000010000 )
#58800000
0!
0&
#58900000
1!
1&
b0000000000000000000000010001 )
#59000000
0!
0&
#59100000
1!
1&
b0000000000000000000000010010 )
#59200000
0!
0&
#59300000
1!
1&
b0000000000000000000000010011 )
#59400000
0!
0&
#59500000
1!
1&
b0000000000000000000000010100 )
#59600000
0!
0&
#59700000
1!
1#
1&
1'
b0000000000000000000000000000 )
1+
#59800000
0!
0&
#59900000
1!
0#
1&
0'
b0000000000000000000000000001 )
b0100 *
0+
#60000000
0!
0&
#60100000
1!
1&
b0000000000000000000000000010 )
#60200000
0!
0&
#60300000
1!
1&
b0000000000000000000000000011 )
#60400000
0!
0&
#60500000
1!
1&
b0000000000000000000000000100 )
#60600000
0!
0&
#60700000
1!
1&
b0000000000000000000000000101 )
#60800000
0!
0&
#60900000
1!
1&
b0000000000000000000000000110 )
#61000000
0!
0&
#61100000
1!
1&
b0000000000000000000000000111 )
#61200000
0!
0&
#61300000
1!
1&
b0000000000000000000000001000 )
#61400000
0!
0&
#61500000
1!
1&
b0000000000000000000000001001 )
#61600000
0!
0&
#61700000
1!
1&
b0000000000000000000000001010 )
#61800000
0!
0&
#61900000
1!
1&
b0000000000000000000000001011 )
#62000000
0!
0&
#62100000
1!
1&
b0000000000000000000000001100 )
#62200000
0!
0&
#62300000
1!
1&
b0000000000000000000000001101 )
#62400000
0!
0&
#62500000
1!
1&
b0000000000000000000000001110 )
#62600000
0!
0&
#62700000
1!
1&
b0000000000000000000000001111 )
#62800000
0!
0&
#62900000
1!
1&
b0000000000000000000000010000 )
#63000000
0!
0&
#63100000
1!
1&
b0000000000000000000000010001 )
#63200000
0!
0&
#63300000
1!
1&
b0000000000000000000000010010 )
#63400000
0!
0&
#63500000
1!
1&
b0000000000000000000000010011 )
#63600000
0!
0&
#63700000
1!
1&
b0000000000000000000000010100 )
#63800000
0!
0&
#63900000
1!
1#
1&
1'
b0000000000000000000000000000 )
1+
#64000000
0!
0&
#64100000
1!
0#
1&
0'
b0000000000000000000000000001 )
b0101 *
0+
#64200000
0!
0&
#64300000
1!
1&
b0000000000000000000000000010 )
#64400000
0!
0&
#64500000
1!
1&
b0000000000000000000000000011 )
#64600000
0!
0&
#64700000
1!
1&
b0000000000000000000000000100 )
#64800000
0!
0&
#64900000
1!
1&
b0000000000000000000000000101 )
#65000000
0!
0&
#65100000
1!
1&
b0000000000000000000000000110 )
#65200000
0!
0&
#65300000
1!
1&
b0000000000000000000000000111 )
#65400000
0!
0&
#65500000
1!
1&
b0000000000000000000000001000 )
#65600000
0!
0&
#65700000
1!
1&
b0000000000000000000000001001 )
#65800000
0!
0&
#65900000
1!
1&
b0000000000000000000000001010 )
#66000000
0!
0&
#66100000
1!
1&
b0000000000000000000000001011 )
#66200000
0!
0&
#66300000
1!
1&
b0000000000000000000000001100 )
#66400000
0!
0&
#66500000
1!
1&
b0000000000000000000000001101 )
#66600000
0!
0&
#66700000
1!
1&
b0000000000000000000000001110 )
#66800000
0!
0&
#66900000
1!
1&
b0000000000000000000000001111 )
#67000000
0!
0&
#67100000
1!
1&
b0000000000000000000000010000 )
#67200000
0!
0&
#67300000
1!
1&
b0000000000000000000000010001 )
#67400000
0!
0&
#67500000
1!
1&
b0000000000000000000000010010 )
#67600000
0!
0&
#67700000
1!
1&
b0000000000000000000000010011 )
#67800000
0!
0&
#67900000
1!
1&
b0000000000000000000000010100 )
#68000000
0!
0&
#68100000
1!
1#
1&
1'
b0000000000000000000000000000 )
1+
#68200000
0!
0&
#68300000
1!
0#
1&
0'
b0000000000000000000000000001 )
b0110 *
0+
#68400000
0!
0&
#68500000
1!
1&
b0000000000000000000000000010 )
#68600000
0!
0&
#68700000
1!
1&
b0000000000000000000000000011 )
#68800000
0!
0&
#68900000
1!
1&
b0000000000000000000000000100 )
#69000000
0!
0&
#69100000
1!
1&
b0000000000000000000000000101 )
#69200000
0!
0&
#69300000
1!
1&
b0000000000000000000000000110 )
#69400000
0!
0&
#69500000
1!
1&
b0000000000000000000000000111 )
#69600000
0!
0&
#69700000
1!
1&
b0000000000000000000000001000 )
#69800000
0!
0&
#69900000
1!
1&
b0000000000000000000000001001 )
#70000000
0!
0&
#70100000
1!
1&
b0000000000000000000000001010 )
#70200000
0!
0&
#70300000
1!
1&
b0000000000000000000000001011 )
#70400000
0!
0&
#70500000
1!
1&
b0000000000000000000000001100 )
#70600000
0!
0&
#70700000
1!
1&
b0000000000000000000000001101 )
#70800000
0!
0&
#70900000
1!
1&
b0000000000000000000000001110 )
#71000000
0!
0&
#71100000
1!
1&
b0000000000000000000000001111 )
#71200000
0!
0&
#71300000
1!
1&
b0000000000000000000000010000 )
#71400000
0!
0&
#71500000
1!
1&
b0000000000000000000000010001 )
#71600000
0!
0&
#71700000
1!
1&
b0000000000000000000000010010 )
#71800000
0!
0&
#71900000
1!
1&
b0000000000000000000000010011 )
#72000000
0!
0&
#72100000
1!
1&
b0000000000000000000000010100 )
#72200000
0!
0&
#72300000
1!
1#
1&
1'
b0000000000000000000000000000 )
1+
#72400000
0!
0&
