TP1/contador.vhdl
library IEEE;
use ieee.std_logic_1164.all;
use ieee.numeric_std.all;

entity contador is
    generic (
        N3 : natural := 28;
        N30 : natural := 4
    );
    port(
        rst : in std_logic;
        clk : in std_logic;
        tres_segundos  : out std_logic;
        treinta_segundos : out std_logic;
        cuenta_3 : out std_logic_vector(N3-1 downto 0);
        cuenta_30 : out std_logic_vector(N30-1 downto 0)
    );
end contador;

architecture behavioral of contador is
    signal aux_cuenta_3  : unsigned(N3-1 downto 0);
    signal aux_cuenta_30 : unsigned(N30-1 downto 0);
    signal aux_tres_segundos:  std_logic := '0';
    signal aux_treinta_segundos:  std_logic := '0';
begin
    process(clk, rst) is
        begin
            if rst = '1' then
                aux_cuenta_3 <= (others => '0');
            elsif clk = '1' and clk'event then
                if aux_tres_segundos = '1' then
                    aux_tres_segundos <= '0';
                end if;
                if aux_cuenta_3 = 40 then
                    aux_cuenta_3 <= (others => '0');
                    aux_tres_segundos <= '1';
                else
                    aux_cuenta_3 <= aux_cuenta_3 + 1;
                end if;
            end if;
        end process;

        process(clk, rst) is
            begin
                if rst = '1' then
                    aux_cuenta_30 <= (others => '0');
                elsif clk = '1' and clk'event then
                    if aux_treinta_segundos = '1' then
                        aux_treinta_segundos <= '0';
                    end if;
                    if aux_tres_segundos = '1' then
                        if aux_cuenta_30 = 9 then
                            aux_cuenta_30 <= (others => '0');
                            aux_treinta_segundos <= '1';
                        else
                            aux_cuenta_30 <= aux_cuenta_30 + 1;
                        end if;
                    end if;
                end if;
            end process;

        cuenta_3         <= std_logic_vector(aux_cuenta_3);
        cuenta_30        <= std_logic_vector(aux_cuenta_30);
        tres_segundos    <= aux_tres_segundos;
        treinta_segundos <= aux_treinta_segundos;

end behavioral;

TP1/tb_contador.vhdl
library ieee;
use ieee.std_logic_1164.all;

entity tb_contador is
end tb_contador;

architecture behavioral of tb_contador is
    constant SIM_TIME_NS: time := 200 ns;
    constant TB_N3 : natural := 28;
    constant TB_N30: natural := 4;

    signal tb_clk               : std_logic := '0';
    signal tb_rst               : std_logic;
    signal tb_tres_segundos     : std_logic := '0';    
    signal tb_treinta_segundos  : std_logic := '0';
    signal tb_cuenta_3          : std_logic_vector(TB_N3-1 downto 0);
    signal tb_cuenta_30         : std_logic_vector(TB_N30-1 downto 0);

    begin
        tb_rst <= '0', '1' after 30 ns, '0' after 50 ns;
        tb_clk <= not tb_clk after 0.15 ns;

        stop_simulation: process
    begin
        wait for SIM_TIME_NS;--run the simulation for this duration
        assert false
        report "Simulation finished."
        severity failure;
    end process;

    I1: entity work.contador(behavioral)
    generic map(
        N3 => TB_N3,
        N30 => TB_N30
    )
    port map(
        rst                 => tb_rst,
        clk                 => tb_clk,
        tres_segundos       => tb_tres_segundos,
        treinta_segundos    => tb_treinta_segundos,
        cuenta_3            => tb_cuenta_3,
        cuenta_30           => tb_cuenta_30   
    );
    end behavioral;

TP1/tb_contador.vcd
$date
  Thu Sep 29 11:24:53 2022
$end
$version
  GHDL v0
$end
$timescale
  1 fs
$end
$scope module standard $end
$upscope $end
$scope module std_logic_1164 $end
$upscope $end
$scope module numeric_std $end
$upscope $end
$scope module tb_contador $end
$var reg 1 ! tb_clk $end
$var reg 1 " tb_rst $end
$var reg 1 # tb_tres_segundos $end
$var reg 1 $ tb_treinta_segundos $end
$var reg 28 % tb_cuenta_3[27:0] $end
$var reg 4 & tb_cuenta_30[3:0] $end
$scope module i1 $end
$var reg 1 ' rst $end
$var reg 1 ( clk $end
$var reg 1 ) tres_segundos $end
$var reg 1 * treinta_segundos $end
$var reg 28 + cuenta_3[27:0] $end
$var reg 4 , cuenta_30[3:0] $end
$var reg 28 - aux_cuenta_3[27:0] $end
$var reg 4 . aux_cuenta_30[3:0] $end
$var reg 1 / aux_tres_segundos $end
$var reg 1 0 aux_treinta_segundos $end
$upscope $end
$upscope $end
$enddefinitions $end
#0
0!
0"
0#
0$
bUUUUUUUUUUUUUUUUUUUUUUUUUUUU %
bUUUU &
0'
0(
0)
0*
bUUUUUUUUUUUUUUUUUUUUUUUUUUUU +
bUUUU ,
bUUUUUUUUUUUUUUUUUUUUUUUUUUUU -
bUUUU .
0/
00
#150000
1!
bXXXXXXXXXXXXXXXXXXXXXXXXXXXX %
1(
bXXXXXXXXXXXXXXXXXXXXXXXXXXXX +
bXXXXXXXXXXXXXXXXXXXXXXXXXXXX -
#300000
0!
0(
#450000
1!
1(
#600000
0!
0(
#750000
1!
1(
#900000
0!
0(
#1050000
1!
1(
#1200000
0!
0(
#1350000
1!
1(
#1500000
0!
0(
#1650000
1!
1(
#1800000
0!
0(
#1950000
1!
1(
#2100000
0!
0(
#2250000
1!
1(
#2400000
0!
0(
#2550000
1!
1(
#2700000
0!
0(
#2850000
1!
1(
#3000000
0!
0(
#3150000
1!
1(
#3300000
0!
0(
#3450000
1!
1(
#3600000
0!
0(
#3750000
1!
1(
#3900000
0!
0(
#4050000
1!
1(
#4200000
0!
0(
#4350000
1!
1(
#4500000
0!
0(
#4650000
1!
1(
#4800000
0!
0(
#4950000
1!
1(
#5100000
0!
0(
#5250000
1!
1(
#5400000
0!
0(
#5550000
1!
1(
#5700000
0!
0(
#5850000
1!
1(
#6000000
0!
0(
#6150000
1!
1(
#6300000
0!
0(
#6450000
1!
1(
#6600000
0!
0(
#6750000
1!
1(
#6900000
0!
0(
#7050000
1!
1(
#7200000
0!
0(
#7350000
1!
1(
#7500000
0!
0(
#7650000
1!
1(
#7800000
0!
0(
#7950000
1!
1(
#8100000
0!
0(
#8250000
1!
1(
#8400000
0!
0(
#8550000
1!
1(
#8700000
0!
0(
#8850000
1!
1(
#9000000
0!
0(
#9150000
1!
1(
#9300000
0!
0(
#9450000
1!
1(
#9600000
0!
0(
#9750000
1!
1(
#9900000
0!
0(
#10050000
1!
1(
#10200000
0!
0(
#10350000
1!
1(
#10500000
0!
0(
#10650000
1!
1(
#10800000
0!
0(
#10950000
1!
1(
#11100000
0!
0(
#11250000
1!
1(
#11400000
0!
0(
#11550000
1!
1(
#11700000
0!
0(
#11850000
1!
1(
#12000000
0!
0(
#12150000
1!
1(
#12300000
0!
0(
#12450000
1!
1(
#12600000
0!
0(
#12750000
1!
1(
#12900000
0!
0(
#13050000
1!
1(
#13200000
0!
0(
#13350000
1!
1(
#13500000
0!
0(
#13650000
1!
1(
#13800000
0!
0(
#13950000
1!
1(
#14100000
0!
0(
#14250000
1!
1(
#14400000
0!
0(
#14550000
1!
1(
#14700000
0!
0(
#14850000
1!
1(
#15000000
0!
0(
#15150000
1!
1(
#15300000
0!
0(
#15450000
1!
1(
#15600000
0!
0(
#15750000
1!
1(
#15900000
0!
0(
#16050000
1!
1(
#16200000
0!
0(
#16350000
1!
1(
#16500000
0!
0(
#16650000
1!
1(
#16800000
0!
0(
#16950000
1!
1(
#17100000
0!
0(
#17250000
1!
1(
#17400000
0!
0(
#17550000
1!
1(
#17700000
0!
0(
#17850000
1!
1(
#18000000
0!
0(
#18150000
1!
1(
#18300000
0!
0(
#18450000
1!
1(
#18600000
0!
0(
#18750000
1!
1(
#18900000
0!
0(
#19050000
1!
1(
#19200000
0!
0(
#19350000
1!
1(
#19500000
0!
0(
#19650000
1!
1(
#19800000
0!
0(
#19950000
1!
1(
#20100000
0!
0(
#20250000
1!
1(
#20400000
0!
0(
#20550000
1!
1(
#20700000
0!
0(
#20850000
1!
1(
#21000000
0!
0(
#21150000
1!
1(
#21300000
0!
0(
#21450000
1!
1(
#21600000
0!
0(
#21750000
1!
1(
#21900000
0!
0(
#22050000
1!
1(
#22200000
0!
0(
#22350000
1!
1(
#22500000
0!
0(
#22650000
1!
1(
#22800000
0!
0(
#22950000
1!
1(
#23100000
0!
0(
#23250000
1!
1(
#23400000
0!
0(
#23550000
1!
1(
#23700000
0!
0(
#23850000
1!
1(
#24000000
0!
0(
#24150000
1!
1(
#24300000
0!
0(
#24450000
1!
1(
#24600000
0!
0(
#24750000
1!
1(
#24900000
0!
0(
#25050000
1!
1(
#25200000
0!
0(
#25350000
1!
1(
#25500000
0!
0(
#25650000
1!
1(
#25800000
0!
0(
#25950000
1!
1(
#26100000
0!
0(
#26250000
1!
1(
#26400000
0!
0(
#26550000
1!
1(
#26700000
0!
0(
#26850000
1!
1(
#27000000
0!
0(
#27150000
1!
1(
#27300000
0!
0(
#27450000
1!
1(
#27600000
0!
0(
#27750000
1!
1(
#27900000
0!
0(
#28050000
1!
1(
#28200000
0!
0(
#28350000
1!
1(
#28500000
0!
0(
#28650000
1!
1(
#28800000
0!
0(
#28950000
1!
1(
#29100000
0!
0(
#29250000
1!
1(
#29400000
0!
0(
#29550000
1!
1(
#29700000
0!
0(
#29850000
1!
1(
#30000000
0!
1"
b0000000000000000000000000000 %
b0000 &
1'
0(
b0000000000000000000000000000 +
b0000 ,
b0000000000000000000000000000 -
b0000 .
#30150000
1!
1(
#30300000
0!
0(
#30450000
1!
1(
#30600000
0!
0(
#30750000
1!
1(
#30900000
0!
0(
#31050000
1!
1(
#31200000
0!
0(
#31350000
1!
1(
#31500000
0!
0(
#31650000
1!
1(
#31800000
0!
0(
#31950000
1!
1(
#32100000
0!
0(
#32250000
1!
1(
#32400000
0!
0(
#32550000
1!
1(
#32700000
0!
0(
#32850000
1!
1(
#33000000
0!
0(
#33150000
1!
1(
#33300000
0!
0(
#33450000
1!
1(
#33600000
0!
0(
#33750000
1!
1(
#33900000
0!
0(
#34050000
1!
1(
#34200000
0!
0(
#34350000
1!
1(
#34500000
0!
0(
#34650000
1!
1(
#34800000
0!
0(
#34950000
1!
1(
#35100000
0!
0(
#35250000
1!
1(
#35400000
0!
0(
#35550000
1!
1(
#35700000
0!
0(
#35850000
1!
1(
#36000000
0!
0(
#36150000
1!
1(
#36300000
0!
0(
#36450000
1!
1(
#36600000
0!
0(
#36750000
1!
1(
#36900000
0!
0(
#37050000
1!
1(
#37200000
0!
0(
#37350000
1!
1(
#37500000
0!
0(
#37650000
1!
1(
#37800000
0!
0(
#37950000
1!
1(
#38100000
0!
0(
#38250000
1!
1(
#38400000
0!
0(
#38550000
1!
1(
#38700000
0!
0(
#38850000
1!
1(
#39000000
0!
0(
#39150000
1!
1(
#39300000
0!
0(
#39450000
1!
1(
#39600000
0!
0(
#39750000
1!
1(
#39900000
0!
0(
#40050000
1!
1(
#40200000
0!
0(
#40350000
1!
1(
#40500000
0!
0(
#40650000
1!
1(
#40800000
0!
0(
#40950000
1!
1(
#41100000
0!
0(
#41250000
1!
1(
#41400000
0!
0(
#41550000
1!
1(
#41700000
0!
0(
#41850000
1!
1(
#42000000
0!
0(
#42150000
1!
1(
#42300000
0!
0(
#42450000
1!
1(
#42600000
0!
0(
#42750000
1!
1(
#42900000
0!
0(
#43050000
1!
1(
#43200000
0!
0(
#43350000
1!
1(
#43500000
0!
0(
#43650000
1!
1(
#43800000
0!
0(
#43950000
1!
1(
#44100000
0!
0(
#44250000
1!
1(
#44400000
0!
0(
#44550000
1!
1(
#44700000
0!
0(
#44850000
1!
1(
#45000000
0!
0(
#45150000
1!
1(
#45300000
0!
0(
#45450000
1!
1(
#45600000
0!
0(
#45750000
1!
1(
#45900000
0!
0(
#46050000
1!
1(
#46200000
0!
0(
#46350000
1!
1(
#46500000
0!
0(
#46650000
1!
1(
#46800000
0!
0(
#46950000
1!
1(
#47100000
0!
0(
#47250000
1!
1(
#47400000
0!
0(
#47550000
1!
1(
#47700000
0!
0(
#47850000
1!
1(
#48000000
0!
0(
#48150000
1!
1(
#48300000
0!
0(
#48450000
1!
1(
#48600000
0!
0(
#48750000
1!
1(
#48900000
0!
0(
#49050000
1!
1(
#49200000
0!
0(
#49350000
1!
1(
#49500000
0!
0(
#49650000
1!
1(
#49800000
0!
0(
#49950000
1!
1(
#50000000
0"
0'
#50100000
0!
0(
#50250000
1!
b0000000000000000000000000001 %
1(
b0000000000000000000000000001 +
b0000000000000000000000000001 -
#50400000
0!
0(
#50550000
1!
b0000000000000000000000000010 %
1(
b0000000000000000000000000010 +
b0000000000000000000000000010 -
#50700000
0!
0(
#50850000
1!
b0000000000000000000000000011 %
1(
b0000000000000000000000000011 +
b0000000000000000000000000011 -
#51000000
0!
0(
#51150000
1!
b0000000000000000000000000100 %
1(
b0000000000000000000000000100 +
b0000000000000000000000000100 -
#51300000
0!
0(
#51450000
1!
b0000000000000000000000000101 %
1(
b0000000000000000000000000101 +
b0000000000000000000000000101 -
#51600000
0!
0(
#51750000
1!
b0000000000000000000000000110 %
1(
b0000000000000000000000000110 +
b0000000000000000000000000110 -
#51900000
0!
0(
#52050000
1!
b0000000000000000000000000111 %
1(
b0000000000000000000000000111 +
b0000000000000000000000000111 -
#52200000
0!
0(
#52350000
1!
b0000000000000000000000001000 %
1(
b0000000000000000000000001000 +
b0000000000000000000000001000 -
#52500000
0!
0(
#52650000
1!
b0000000000000000000000001001 %
1(
b0000000000000000000000001001 +
b0000000000000000000000001001 -
#52800000
0!
0(
#52950000
1!
b0000000000000000000000001010 %
1(
b0000000000000000000000001010 +
b0000000000000000000000001010 -
#53100000
0!
0(
#53250000
1!
b0000000000000000000000001011 %
1(
b0000000000000000000000001011 +
b0000000000000000000000001011 -
#53400000
0!
0(
#53550000
1!
b0000000000000000000000001100 %
1(
b0000000000000000000000001100 +
b0000000000000000000000001100 -
#53700000
0!
0(
#53850000
1!
b0000000000000000000000001101 %
1(
b0000000000000000000000001101 +
b0000000000000000000000001101 -
#54000000
0!
0(
#54150000
1!
b0000000000000000000000001110 %
1(
b0000000000000000000000001110 +
b0000000000000000000000001110 -
#54300000
0!
0(
#54450000
1!
b0000000000000000000000001111 %
1(
b0000000000000000000000001111 +
b0000000000000000000000001111 -
#54600000
0!
0(
#54750000
1!
b0000000000000000000000010000 %
1(
b0000000000000000000000010000 +
b0000000000000000000000010000 -
#54900000
0!
0(
#55050000
1!
b0000000000000000000000010001 %
1(
b0000000000000000000000010001 +
b0000000000000000000000010001 -
#55200000
0!
0(
#55350000
1!
b0000000000000000000000010010 %
1(
b0000000000000000000000010010 +
b0000000000000000000000010010 -
#55500000
0!
0(
#55650000
1!
b0000000000000000000000010011 %
1(
b0000000000000000000000010011 +
b0000000000000000000000010011 -
#55800000
0!
0(
#55950000
1!
b0000000000000000000000010100 %
1(
b0000000000000000000000010100 +
b0000000000000000000000010100 -
#56100000
0!
0(
#56250000
1!
b0000000000000000000000010101 %
1(
b0000000000000000000000010101 +
b0000000000000000000000010101 -
#56400000
0!
0(
#56550000
1!
b0000000000000000000000010110 %
1(
b0000000000000000000000010110 +
b0000000000000000000000010110 -
#56700000
0!
0(
#56850000
1!
b0000000000000000000000010111 %
1(
b0000000000000000000000010111 +
b0000000000000000000000010111 -
#57000000
0!
0(
#57150000
1!
b0000000000000000000000011000 %
1(
b0000000000000000000000011000 +
b0000000000000000000000011000 -
#57300000
0!
0(
#57450000
1!
b0000000000000000000000011001 %
1(
b0000000000000000000000011001 +
b0000000000000000000000011001 -
#57600000
0!
0(
#57750000
1!
b0000000000000000000000011010 %
1(
b0000000000000000000000011010 +
b0000000000000000000000011010 -
#57900000
0!
0(
#58050000
1!
b0000000000000000000000011011 %
1(
b0000000000000000000000011011 +
b0000000000000000000000011011 -
#58200000
0!
0(
#58350000
1!
b0000000000000000000000011100 %
1(
b0000000000000000000000011100 +
b0000000000000000000000011100 -
#58500000
0!
0(
#58650000
1!
b0000000000000000000000011101 %
1(
b0000000000000000000000011101 +
b0000000000000000000000011101 -
#58800000
0!
0(
#58950000
1!
b0000000000000000000000011110 %
1(
b0000000000000000000000011110 +
b0000000000000000000000011110 -
#59100000
0!
0(
#59250000
1!
b0000000000000000000000011111 %
1(
b0000000000000000000000011111 +
b0000000000000000000000011111 -
#59400000
0!
0(
#59550000
1!
b0000000000000000000000100000 %
1(
b0000000000000000000000100000 +
b0000000000000000000000100000 -
#59700000
0!
0(
#59850000
1!
b0000000000000000000000100001 %
1(
b0000000000000000000000100001 +
b0000000000000000000000100001 -
#60000000
0!
0(
#60150000
1!
b0000000000000000000000100010 %
1(
b0000000000000000000000100010 +
b0000000000000000000000100010 -
#60300000
0!
0(
#60450000
1!
b0000000000000000000000100011 %
1(
b0000000000000000000000100011 +
b0000000000000000000000100011 -
#60600000
0!
0(
#60750000
1!
b0000000000000000000000100100 %
1(
b0000000000000000000000100100 +
b0000000000000000000000100100 -
#60900000
0!
0(
#61050000
1!
b0000000000000000000000100101 %
1(
b0000000000000000000000100101 +
b0000000000000000000000100101 -
#61200000
0!
0(
#61350000
1!
b0000000000000000000000100110 %
1(
b0000000000000000000000100110 +
b0000000000000000000000100110 -
#61500000
0!
0(
#61650000
1!
b0000000000000000000000100111 %
1(
b0000000000000000000000100111 +
b0000000000000000000000100111 -
#61800000
0!
0(
#61950000
1!
b0000000000000000000000101000 %
1(
b0000000000000000000000101000 +
b0000000000000000000000101000 -
#62100000
0!
0(
#62250000
1!
1#
b0000000000000000000000000000 %
1(
1)
b0000000000000000000000000000 +
b0000000000000000000000000000 -
1/
#62400000
0!
0(
#62550000
1!
0#
b0000000000000000000000000001 %
b0001 &
1(
0)
b0000000000000000000000000001 +
b0001 ,
b0000000000000000000000000001 -
b0001 .
0/
#62700000
0!
0(
#62850000
1!
b0000000000000000000000000010 %
1(
b0000000000000000000000000010 +
b0000000000000000000000000010 -
#63000000
0!
0(
#63150000
1!
b0000000000000000000000000011 %
1(
b0000000000000000000000000011 +
b0000000000000000000000000011 -
#63300000
0!
0(
#63450000
1!
b0000000000000000000000000100 %
1(
b0000000000000000000000000100 +
b0000000000000000000000000100 -
#63600000
0!
0(
#63750000
1!
b0000000000000000000000000101 %
1(
b0000000000000000000000000101 +
b0000000000000000000000000101 -
#63900000
0!
0(
#64050000
1!
b0000000000000000000000000110 %
1(
b0000000000000000000000000110 +
b0000000000000000000000000110 -
#64200000
0!
0(
#64350000
1!
b0000000000000000000000000111 %
1(
b0000000000000000000000000111 +
b0000000000000000000000000111 -
#64500000
0!
0(
#64650000
1!
b0000000000000000000000001000 %
1(
b0000000000000000000000001000 +
b0000000000000000000000001000 -
#64800000
0!
0(
#64950000
1!
b0000000000000000000000001001 %
1(
b0000000000000000000000001001 +
b0000000000000000000000001001 -
#65100000
0!
0(
#65250000
1!
b0000000000000000000000001010 %
1(
b0000000000000000000000001010 +
b0000000000000000000000001010 -
#65400000
0!
0(
#65550000
1!
b0000000000000000000000001011 %
1(
b0000000000000000000000001011 +
b0000000000000000000000001011 -
#65700000
0!
0(
#65850000
1!
b0000000000000000000000001100 %
1(
b0000000000000000000000001100 +
b0000000000000000000000001100 -
#66000000
0!
0(
#66150000
1!
b0000000000000000000000001101 %
1(
b0000000000000000000000001101 +
b0000000000000000000000001101 -
#66300000
0!
0(
#66450000
1!
b0000000000000000000000001110 %
1(
b0000000000000000000000001110 +
b0000000000000000000000001110 -
#66600000
0!
0(
#66750000
1!
b0000000000000000000000001111 %
1(
b0000000000000000000000001111 +
b0000000000000000000000001111 -
#66900000
0!
0(
#67050000
1!
b0000000000000000000000010000 %
1(
b0000000000000000000000010000 +
b0000000000000000000000010000 -
#67200000
0!
0(
#67350000
1!
b0000000000000000000000010001 %
1(
b0000000000000000000000010001 +
b0000000000000000000000010001 -
#67500000
0!
0(
#67650000
1!
b0000000000000000000000010010 %
1(
b0000000000000000000000010010 +
b0000000000000000000000010010 -
#67800000
0!
0(
#67950000
1!
b0000000000000000000000010011 %
1(
b0000000000000000000000010011 +
b0000000000000000000000010011 -
#68100000
0!
0(
#68250000
1!
b0000000000000000000000010100 %
1(
b0000000000000000000000010100 +
b0000000000000000000000010100 -
#68400000
0!
0(
#68550000
1!
b0000000000000000000000010101 %
1(
b0000000000000000000000010101 +
b0000000000000000000000010101 -
#68700000
0!
0(
#68850000
1!
b0000000000000000000000010110 %
1(
b0000000000000000000000010110 +
b0000000000000000000000010110 -
#69000000
0!
0(
#69150000
1!
b0000000000000000000000010111 %
1(
b0000000000000000000000010111 +
b0000000000000000000000010111 -
#69300000
0!
0(
#69450000
1!
b0000000000000000000000011000 %
1(
b0000000000000000000000011000 +
b0000000000000000000000011000 -
#69600000
0!
0(
#69750000
1!
b0000000000000000000000011001 %
1(
b0000000000000000000000011001 +
b0000000000000000000000011001 -
#69900000
0!
0(
#70050000
1!
b0000000000000000000000011010 %
1(
b0000000000000000000000011010 +
b0000000000000000000000011010 -
#70200000
0!
0(
#70350000
1!
b0000000000000000000000011011 %
1(
b0000000000000000000000011011 +
b0000000000000000000000011011 -
#70500000
0!
0(
#70650000
1!
b0000000000000000000000011100 %
1(
b0000000000000000000000011100 +
b0000000000000000000000011100 -
#70800000
0!
0(
#70950000
1!
b0000000000000000000000011101 %
1(
b0000000000000000000000011101 +
b0000000000000000000000011101 -
#71100000
0!
0(
#71250000
1!
b0000000000000000000000011110 %
1(
b0000000000000000000000011110 +
b0000000000000000000000011110 -
#71400000
0!
0(
#71550000
1!
b0000000000000000000000011111 %
1(
b0000000000000000000000011111 +
b0000000000000000000000011111 -
#71700000
0!
0(
#71850000
1!
b0000000000000000000000100000 %
1(
b0000000000000000000000100000 +
b0000000000000000000000100000 -
#72000000
0!
0(
#72150000
1!
b0000000000000000000000100001 %
1(
b0000000000000000000000100001 +
b0000000000000000000000100001 -
#72300000
0!
0(
#72450000
1!
b0000000000000000000000100010 %
1(
b0000000000000000000000100010 +
b0000000000000000000000100010 -
#72600000
0!
0(
#72750000
1!
b0000000000000000000000100011 %
1(
b0000000000000000000000100011 +
b0000000000000000000000100011 -
#72900000
0!
0(
#73050000
1!
b0000000000000000000000100100 %
1(
b0000000000000000000000100100 +
b0000000000000000000000100100 -
#73200000
0!
0(
#73350000
1!
b0000000000000000000000100101 %
1(
b0000000000000000000000100101 +
b0000000000000000000000100101 -
#73500000
0!
0(
#73650000
1!
b0000000000000000000000100110 %
1(
b0000000000000000000000100110 +
b0000000000000000000000100110 -
#73800000
0!
0(
#73950000
1!
b0000000000000000000000100111 %
1(
b0000000000000000000000100111 +
b0000000000000000000000100111 -
#74100000
0!
0(
#74250000
1!
b0000000000000000000000101000 %
1(
b0000000000000000000000101000 +
b0000000000000000000000101000 -
#74400000
0!
0(
#74550000
1!
1#
b0000000000000000000000000000 %
1(
1)
b0000000000000000000000000000 +
b0000000000000000000000000000 -
1/
#74700000
0!
0(
#74850000
1!
0#
b0000000000000000000000000001 %
b0010 &
1(
0)
b0000000000000000000000000001 +
b0010 ,
b0000000000000000000000000001 -
b0010 .
0/
#75000000
0!
0(
#75150000
1!
b0000000000000000000000000010 %
1(
b0000000000000000000000000010 +
b0000000000000000000000000010 -
#75300000
0!
0(
#75450000
1!
b0000000000000000000000000011 %
1(
b0000000000000000000000000011 +
b0000000000000000000000000011 -
#75600000
0!
0(
#75750000
1!
b0000000000000000000000000100 %
1(
b0000000000000000000000000100 +
b0000000000000000000000000100 -
#75900000
0!
0(
#76050000
1!
b0000000000000000000000000101 %
1(
b0000000000000000000000000101 +
b0000000000000000000000000101 -
#76200000
0!
0(
#76350000
1!
b0000000000000000000000000110 %
1(
b0000000000000000000000000110 +
b0000000000000000000000000110 -
#76500000
0!
0(
#76650000
1!
b0000000000000000000000000111 %
1(
b0000000000000000000000000111 +
b0000000000000000000000000111 -
#76800000
0!
0(
#76950000
1!
b0000000000000000000000001000 %
1(
b0000000000000000000000001000 +
b0000000000000000000000001000 -
#77100000
0!
0(
#77250000
1!
b0000000000000000000000001001 %
1(
b0000000000000000000000001001 +
b0000000000000000000000001001 -
#77400000
0!
0(
#77550000
1!
b0000000000000000000000001010 %
1(
b0000000000000000000000001010 +
b0000000000000000000000001010 -
#77700000
0!
0(
#77850000
1!
b0000000000000000000000001011 %
1(
b0000000000000000000000001011 +
b0000000000000000000000001011 -
#78000000
0!
0(
#78150000
1!
b0000000000000000000000001100 %
1(
b0000000000000000000000001100 +
b0000000000000000000000001100 -
#78300000
0!
0(
#78450000
1!
b0000000000000000000000001101 %
1(
b0000000000000000000000001101 +
b0000000000000000000000001101 -
#78600000
0!
0(
#78750000
1!
b0000000000000000000000001110 %
1(
b0000000000000000000000001110 +
b0000000000000000000000001110 -
#78900000
0!
0(
#79050000
1!
b0000000000000000000000001111 %
1(
b0000000000000000000000001111 +
b0000000000000000000000001111 -
#79200000
0!
0(
#79350000
1!
b0000000000000000000000010000 %
1(
b0000000000000000000000010000 +
b0000000000000000000000010000 -
#79500000
0!
0(
#79650000
1!
b0000000000000000000000010001 %
1(
b0000000000000000000000010001 +
b0000000000000000000000010001 -
#79800000
0!
0(
#79950000
1!
b0000000000000000000000010010 %
1(
b0000000000000000000000010010 +
b0000000000000000000000010010 -
#80100000
0!
0(
#80250000
1!
b0000000000000000000000010011 %
1(
b0000000000000000000000010011 +
b0000000000000000000000010011 -
#80400000
0!
0(
#80550000
1!
b0000000000000000000000010100 %
1(
b0000000000000000000000010100 +
b0000000000000000000000010100 -
#80700000
0!
0(
#80850000
1!
b0000000000000000000000010101 %
1(
b0000000000000000000000010101 +
b0000000000000000000000010101 -
#81000000
0!
0(
#81150000
1!
b0000000000000000000000010110 %
1(
b0000000000000000000000010110 +
b0000000000000000000000010110 -
#81300000
0!
0(
#81450000
1!
b0000000000000000000000010111 %
1(
b0000000000000000000000010111 +
b0000000000000000000000010111 -
#81600000
0!
0(
#81750000
1!
b0000000000000000000000011000 %
1(
b0000000000000000000000011000 +
b0000000000000000000000011000 -
#81900000
0!
0(
#82050000
1!
b0000000000000000000000011001 %
1(
b0000000000000000000000011001 +
b0000000000000000000000011001 -
#82200000
0!
0(
#82350000
1!
b0000000000000000000000011010 %
1(
b0000000000000000000000011010 +
b0000000000000000000000011010 -
#82500000
0!
0(
#82650000
1!
b0000000000000000000000011011 %
1(
b0000000000000000000000011011 +
b0000000000000000000000011011 -
#82800000
0!
0(
#82950000
1!
b0000000000000000000000011100 %
1(
b0000000000000000000000011100 +
b0000000000000000000000011100 -
#83100000
0!
0(
#83250000
1!
b0000000000000000000000011101 %
1(
b0000000000000000000000011101 +
b0000000000000000000000011101 -
#83400000
0!
0(
#83550000
1!
b0000000000000000000000011110 %
1(
b0000000000000000000000011110 +
b0000000000000000000000011110 -
#83700000
0!
0(
#83850000
1!
b0000000000000000000000011111 %
1(
b0000000000000000000000011111 +
b0000000000000000000000011111 -
#84000000
0!
0(
#84150000
1!
b0000000000000000000000100000 %
1(
b0000000000000000000000100000 +
b0000000000000000000000100000 -
#84300000
0!
0(
#84450000
1!
b0000000000000000000000100001 %
1(
b0000000000000000000000100001 +
b0000000000000000000000100001 -
#84600000
0!
0(
#84750000
1!
b0000000000000000000000100010 %
1(
b0000000000000000000000100010 +
b0000000000000000000000100010 -
#84900000
0!
0(
#85050000
1!
b0000000000000000000000100011 %
1(
b0000000000000000000000100011 +
b0000000000000000000000100011 -
#85200000
0!
0(
#85350000
1!
b0000000000000000000000100100 %
1(
b0000000000000000000000100100 +
b0000000000000000000000100100 -
#85500000
0!
0(
#85650000
1!
b0000000000000000000000100101 %
1(
b0000000000000000000000100101 +
b0000000000000000000000100101 -
#85800000
0!
0(
#85950000
1!
b0000000000000000000000100110 %
1(
b0000000000000000000000100110 +
b0000000000000000000000100110 -
#86100000
0!
0(
#86250000
1!
b0000000000000000000000100111 %
1(
b0000000000000000000000100111 +
b0000000000000000000000100111 -
#86400000
0!
0(
#86550000
1!
b0000000000000000000000101000 %
1(
b0000000000000000000000101000 +
b0000000000000000000000101000 -
#86700000
0!
0(
#86850000
1!
1#
b0000000000000000000000000000 %
1(
1)
b0000000000000000000000000000 +
b0000000000000000000000000000 -
1/
#87000000
0!
0(
#87150000
1!
0#
b0000000000000000000000000001 %
b0011 &
1(
0)
b0000000000000000000000000001 +
b0011 ,
b0000000000000000000000000001 -
b0011 .
0/
#87300000
0!
0(
#87450000
1!
b0000000000000000000000000010 %
1(
b0000000000000000000000000010 +
b0000000000000000000000000010 -
#87600000
0!
0(
#87750000
1!
b0000000000000000000000000011 %
1(
b0000000000000000000000000011 +
b0000000000000000000000000011 -
#87900000
0!
0(
#88050000
1!
b0000000000000000000000000100 %
1(
b0000000000000000000000000100 +
b0000000000000000000000000100 -
#88200000
0!
0(
#88350000
1!
b0000000000000000000000000101 %
1(
b0000000000000000000000000101 +
b0000000000000000000000000101 -
#88500000
0!
0(
#88650000
1!
b0000000000000000000000000110 %
1(
b0000000000000000000000000110 +
b0000000000000000000000000110 -
#88800000
0!
0(
#88950000
1!
b0000000000000000000000000111 %
1(
b0000000000000000000000000111 +
b0000000000000000000000000111 -
#89100000
0!
0(
#89250000
1!
b0000000000000000000000001000 %
1(
b0000000000000000000000001000 +
b0000000000000000000000001000 -
#89400000
0!
0(
#89550000
1!
b0000000000000000000000001001 %
1(
b0000000000000000000000001001 +
b0000000000000000000000001001 -
#89700000
0!
0(
#89850000
1!
b0000000000000000000000001010 %
1(
b0000000000000000000000001010 +
b0000000000000000000000001010 -
#90000000
0!
0(
#90150000
1!
b0000000000000000000000001011 %
1(
b0000000000000000000000001011 +
b0000000000000000000000001011 -
#90300000
0!
0(
#90450000
1!
b0000000000000000000000001100 %
1(
b0000000000000000000000001100 +
b0000000000000000000000001100 -
#90600000
0!
0(
#90750000
1!
b0000000000000000000000001101 %
1(
b0000000000000000000000001101 +
b0000000000000000000000001101 -
#90900000
0!
0(
#91050000
1!
b0000000000000000000000001110 %
1(
b0000000000000000000000001110 +
b0000000000000000000000001110 -
#91200000
0!
0(
#91350000
1!
b0000000000000000000000001111 %
1(
b0000000000000000000000001111 +
b0000000000000000000000001111 -
#91500000
0!
0(
#91650000
1!
b0000000000000000000000010000 %
1(
b0000000000000000000000010000 +
b0000000000000000000000010000 -
#91800000
0!
0(
