TP1/contador.vhdl
library IEEE;
use ieee.std_logic_1164.all;
use ieee.numeric_std.all;

entity contador is
    generic (
        N1 : natural := 5;
        N30 : natural := 26
    );
    port(
        rst : in std_logic;
        clk : in std_logic;
        un_segundo  : out std_logic;
        treinta_segundos : out std_logic;
        cuenta_1 : out std_logic_vector(N1-1 downto 0);
        cuenta_30 : out std_logic_vector(N30-1 downto 0)
    );
end contador;

architecture behavioral of contador is
    signal aux_cuenta_1  : unsigned(N1-1 downto 0);
    signal aux_cuenta_30 : unsigned(N30-1 downto 0);
    signal aux_un_segundo:  std_logic;
    signal aux_treinta_segundos:  std_logic;
begin

    process(clk, rst) is
    begin
        if rst = '1' then
            aux_cuenta_1 <= (others => '0');
        elsif clk = '1' and clk'event then
            if aux_cuenta_1 = 49999 then
                aux_cuenta_1 <= (others => '0');
                aux_un_segundo <= '1';
            else
                aux_cuenta_1 <= aux_cuenta_1 + 1;
            end if;
        end if;
    end process;

    cuenta_1 <= std_logic_vector(aux_cuenta_1);

    process(clk, rst) is
    begin
        if rst = '1' then
            aux_cuenta_30 <= (others => '0');
        elsif clk = '1' and clk'event then
            if aux_un_segundo = '1' then
                if aux_cuenta_30 = 29 then
                    aux_cuenta_30 <= (others => '0');
                    aux_treinta_segundos <= '1';
                else
                    aux_cuenta_30 <= aux_cuenta_30 + 1;
                end if;
            end if;
        end if;
    end process;

        cuenta_30        <= std_logic_vector(aux_cuenta_30);
        un_segundo       <= '1';
        treinta_segundos <= '1';

end behavioral;

TP1/tb_contador.vhdl
library ieee;
use ieee.std_logic_1164.all;

entity tb_contador is
end tb_contador;

architecture behavioral of tb_contador is
    constant SIM_TIME_NS: time := 200 ns;
    constant TB_N1 : natural := 5;
    constant TB_N30: natural := 26;

    signal tb_clk               : std_logic := '0';
    signal tb_rst               : std_logic;
    signal tb_un_segundo        : std_logic;    
    signal tb_treinta_segundos  : std_logic;
    signal tb_cuenta_1          : std_logic_vector(TB_N1-1 downto 0);
    signal tb_cuenta_30         : std_logic_vector(TB_N30-1 downto 0);

    begin
        tb_rst <= '0', '1' after 30 ns, '0' after 50 ns;
        tb_clk <= not tb_clk after 5 ns;

        stop_simulation: process
    begin
        wait for SIM_TIME_NS;--run the simulation for this duration
        assert false
        report "Simulation finished."
        severity failure;
    end process;

    I1: entity work.contador(behavioral)
    generic map(
        N1 => TB_N1,
        N30 => TB_N30
    )
    port map(
        rst                 => tb_rst,
        clk                 => tb_clk,
        un_segundo          => tb_un_segundo,
        treinta_segundos    => tb_treinta_segundos,
        cuenta_1            => tb_cuenta_1,
        cuenta_30           => tb_cuenta_30   
    );
    end behavioral;

TP1/tb_contador.vcd
$date
  Mon Sep 26 15:39:52 2022
$end
$version
  GHDL v0
$end
$timescale
  1 fs
$end
$scope module standard $end
$upscope $end
$scope module std_logic_1164 $end
$upscope $end
$scope module numeric_std $end
$upscope $end
$scope module tb_contador $end
$var reg 1 ! tb_clk $end
$var reg 1 " tb_rst $end
$var reg 1 # tb_un_segundo $end
$var reg 1 $ tb_treinta_segundos $end
$var reg 5 % tb_cuenta_1[4:0] $end
$var reg 26 & tb_cuenta_30[25:0] $end
$scope module i1 $end
$var reg 1 ' rst $end
$var reg 1 ( clk $end
$var reg 1 ) un_segundo $end
$var reg 1 * treinta_segundos $end
$var reg 5 + cuenta_1[4:0] $end
$var reg 26 , cuenta_30[25:0] $end
$var reg 5 - aux_cuenta_1[4:0] $end
$var reg 26 . aux_cuenta_30[25:0] $end
$var reg 1 / aux_un_segundo $end
$var reg 1 0 aux_treinta_segundos $end
$upscope $end
$upscope $end
$enddefinitions $end
#0
0!
0"
1#
1$
bUUUUU %
bUUUUUUUUUUUUUUUUUUUUUUUUUU &
0'
0(
1)
1*
bUUUUU +
bUUUUUUUUUUUUUUUUUUUUUUUUUU ,
bUUUUU -
bUUUUUUUUUUUUUUUUUUUUUUUUUU .
U/
U0
#5000000
1!
bXXXXX %
1(
bXXXXX +
bXXXXX -
#10000000
0!
0(
#15000000
1!
1(
#20000000
0!
0(
#25000000
1!
1(
#30000000
0!
1"
b00000 %
b00000000000000000000000000 &
1'
0(
b00000 +
b00000000000000000000000000 ,
b00000 -
b00000000000000000000000000 .
#35000000
1!
1(
#40000000
0!
0(
#45000000
1!
1(
#50000000
0!
0"
0'
0(
#55000000
1!
b00001 %
1(
b00001 +
b00001 -
#60000000
0!
0(
#65000000
1!
b00010 %
1(
b00010 +
b00010 -
#70000000
0!
0(
#75000000
1!
b00011 %
1(
b00011 +
b00011 -
#80000000
0!
0(
#85000000
1!
b00100 %
1(
b00100 +
b00100 -
#90000000
0!
0(
#95000000
1!
b00101 %
1(
b00101 +
b00101 -
#100000000
0!
0(
#105000000
1!
b00110 %
1(
b00110 +
b00110 -
#110000000
0!
0(
#115000000
1!
b00111 %
1(
b00111 +
b00111 -
#120000000
0!
0(
#125000000
1!
b01000 %
1(
b01000 +
b01000 -
#130000000
0!
0(
#135000000
1!
b01001 %
1(
b01001 +
b01001 -
#140000000
0!
0(
#145000000
1!
b01010 %
1(
b01010 +
b01010 -
#150000000
0!
0(
#155000000
1!
b01011 %
1(
b01011 +
b01011 -
#160000000
0!
0(
#165000000
1!
b01100 %
1(
b01100 +
b01100 -
#170000000
0!
0(
#175000000
1!
b01101 %
1(
b01101 +
b01101 -
#180000000
0!
0(
#185000000
1!
b01110 %
1(
b01110 +
b01110 -
#190000000
0!
0(
#195000000
1!
b01111 %
1(
b01111 +
b01111 -
